geezlibs
